[                                                                                    
  {                                                       
    "Event": "add_product",
    "Details": {
      "barcodeId": "6976068958185",
      "name": "BioAoua Algae Moisturizing Mask",
      "brand": "BioAoua",
      "weight": "25g",
      "price": 6
    }
  },
  {                                                       
    "Event": "add_product",
    "Details": {
      "barcodeId": "6976504687228",
      "name": "BioAoua Algae Moisturizing Mask",
      "brand": "Bioaoua",
      "weight": "",
      "price": 6
    }
  },
  {                                                       
    "Event": "add_product",
    "Details": {
      "barcodeId": "6976068957676",
      "name": "Blueberry Facial Mask",
      "brand": "",
      "weight": "",
      "price": 6
    }
  },
  {                                                       
    "Event": "add_product",
    "Details": {
      "barcodeId": "6976068956563",
      "name": "Blueberry Facial Mask",
      "brand": "",
      "weight": "",
      "price": 6
    }
  }
]
